pyappdevkit/__init__.py
pyappdevkit/parameters.py
pyappdevkit/pyappdevkit_info.py
pyappdevkit-2.2.dist-info/licenses/LICENSE
pyappdevkit-2.2.dist-info/METADATA
pyappdevkit-2.2.dist-info/WHEEL
pyappdevkit-2.2.dist-info/top_level.txt
pyappdevkit-2.2.dist-info/RECORD
