Metadata-Version: 2.4
Name: pyappdevkit
Version: 2.2
Summary: PyAppDevKit is a development kit for Python developers that aims to make software/application development easier.
Author: LinuxUsersLinuxMint
License:                     GNU GENERAL PUBLIC LICENSE
Project-URL: Homepage, https://github.com/LinuxUsersLinuxMint/PyAppDevKit
Project-URL: Source, https://github.com/LinuxUsersLinuxMint/PyAppDevKit
Requires-Python: >=3.7
License-File: LICENSE
Dynamic: license-file
